LICENSE
crsf_parser/__init__.py
crsf_parser/frames.py
crsf_parser/handling.py
crsf_parser/payloads.py
crsf_parser-0.3.0.dist-info/LICENSE
crsf_parser-0.3.0.dist-info/WHEEL
crsf_parser-0.3.0.dist-info/METADATA
crsf_parser-0.3.0.dist-info/RECORD
